oxrdflib/__init__.py
oxrdflib/_converter.py
oxrdflib/_type.py
oxrdflib/parser.py
oxrdflib/py.typed
oxrdflib/serializer.py
oxrdflib/store.py
oxrdflib-0.5.0.dist-info/WHEEL
oxrdflib-0.5.0.dist-info/entry_points.txt
oxrdflib-0.5.0.dist-info/METADATA
oxrdflib-0.5.0.dist-info/RECORD
