Metadata-Version: 2.3
Name: oxrdflib
Version: 0.5.0
Summary: rdflib stores based on pyoxigraph
Author: Tpt, Nikola
Author-email: Tpt <thomas@pellissier-tanon.fr>, Nikola <me@thisisnikola.com>
License: BSD-3-Clause
Classifier: Programming Language :: Python
Classifier: Programming Language :: Python :: 3 :: Only
Classifier: Programming Language :: Python :: 3.8
Classifier: Programming Language :: Python :: 3.9
Classifier: Programming Language :: Python :: 3.10
Classifier: Programming Language :: Python :: 3.11
Classifier: Programming Language :: Python :: 3.12
Classifier: Programming Language :: Python :: 3.13
Classifier: Programming Language :: Python :: 3.14
Classifier: License :: OSI Approved :: BSD License
Classifier: Topic :: Software Development :: Libraries :: Python Modules
Classifier: Topic :: Database :: Database Engines/Servers
Requires-Dist: pyoxigraph~=0.5.0
Requires-Dist: rdflib>=6.3,<8.0
Maintainer: Tpt
Maintainer-email: Tpt <thomas@pellissier-tanon.fr>
Requires-Python: >=3.8
Project-URL: Changelog, https://github.com/oxigraph/oxrdflib/blob/main/CHANGELOG.md
Project-URL: Documentation, https://github.com/oxigraph/oxrdflib/blob/main/README.md
Project-URL: Homepage, https://github.com/oxigraph/oxrdflib
Project-URL: Source, https://github.com/oxigraph/oxrdflib
Project-URL: Tracker, https://github.com/oxigraph/oxrdflib/issues
